zeroguess/__init__.py
zeroguess/data/__init__.py
zeroguess/data/generators.py
zeroguess/data/preprocessors.py
zeroguess/data/validators.py
zeroguess/estimators/__init__.py
zeroguess/estimators/base.py
zeroguess/estimators/factory.py
zeroguess/estimators/nn_estimator.py
zeroguess/estimators/architectures/__init__.py
zeroguess/estimators/architectures/base.py
zeroguess/estimators/architectures/cnn.py
zeroguess/estimators/architectures/mlp.py
zeroguess/estimators/architectures/registry.py
zeroguess/estimators/architectures/transformer.py
zeroguess/functions/__init__.py
zeroguess/functions/base.py
zeroguess/functions/constants.py
zeroguess/functions/damped_sine.py
zeroguess/functions/double_gaussian.py
zeroguess/functions/double_sigmoid.py
zeroguess/functions/gaussian.py
zeroguess/functions/linear.py
zeroguess/functions/multimodal.py
zeroguess/functions/sigmoid.py
zeroguess/functions/utils.py
zeroguess/functions/wavelet.py
zeroguess/integration/__init__.py
zeroguess/integration/lmfit_adapter.py
zeroguess/utils/__init__.py
zeroguess/utils/logging.py
zeroguess/utils/visualization.py
zeroguess-0.8.3.dist-info/LICENSE
zeroguess-0.8.3.dist-info/METADATA
zeroguess-0.8.3.dist-info/WHEEL
zeroguess-0.8.3.dist-info/top_level.txt
zeroguess-0.8.3.dist-info/RECORD
