Metadata-Version: 2.2
Name: zeroguess
Version: 0.8.3
Summary: Machine Learning for Curve Fitting Parameter Estimation
Home-page: https://github.com/deniz195/zeroguess
Author: Deniz Bozyigit
Author-email: Deniz Bozyigit <deniz195@gmail.com>
License: MIT
Project-URL: Homepage, https://github.com/deniz195/zeroguess
Project-URL: Bug Tracker, https://github.com/deniz195/zeroguess/issues
Classifier: Programming Language :: Python :: 3
Classifier: Programming Language :: Python :: 3.10
Classifier: License :: OSI Approved :: MIT License
Classifier: Operating System :: OS Independent
Classifier: Topic :: Scientific/Engineering
Classifier: Topic :: Scientific/Engineering :: Artificial Intelligence
Classifier: Topic :: Scientific/Engineering :: Mathematics
Requires-Python: >=3.10
License-File: LICENSE
Requires-Dist: numpy>=1.20.0
Requires-Dist: scipy>=1.7.0
Requires-Dist: torch>=1.10.0
Requires-Dist: matplotlib>=3.5.0
Requires-Dist: tqdm>=4.62.0
Provides-Extra: lmfit
Requires-Dist: lmfit>=1.0.0; extra == "lmfit"
Provides-Extra: dev
Requires-Dist: pytest>=7.0.0; extra == "dev"
Requires-Dist: pytest-cov>=4.0.0; extra == "dev"
Requires-Dist: pytest-benchmark>=4.0.0; extra == "dev"
Requires-Dist: pytest-xdist>=3.0.0; extra == "dev"
Requires-Dist: black>=23.3.0; extra == "dev"
Requires-Dist: isort>=5.12.0; extra == "dev"
Requires-Dist: flake8>=6.0.0; extra == "dev"
Requires-Dist: flake8-bugbear>=23.3.23; extra == "dev"
Requires-Dist: flake8-pyproject>=1.2.0; extra == "dev"
Requires-Dist: mypy>=1.3.0; extra == "dev"
Requires-Dist: vulture>=2.7; extra == "dev"
Requires-Dist: bandit>=1.7.5; extra == "dev"
Requires-Dist: safety>=2.3.5; extra == "dev"
Requires-Dist: dotenv>=1.0.1; extra == "dev"
Requires-Dist: pre-commit>=3.3.2; extra == "dev"
Requires-Dist: pip-tools>=6.13.0; extra == "dev"
Requires-Dist: sphinx>=7.0.0; extra == "dev"
Requires-Dist: sphinx-rtd-theme>=1.2.0; extra == "dev"
Dynamic: author
Dynamic: home-page
Dynamic: requires-python
